proxy_ninja/__init__.py
proxy_ninja-0.1.0.dist-info/METADATA
proxy_ninja-0.1.0.dist-info/WHEEL
proxy_ninja-0.1.0.dist-info/top_level.txt
proxy_ninja-0.1.0.dist-info/RECORD
